{"ongoing_trials": {"tuner0": "02"}, "hyperparameters": {"space": [{"class_name": "Int", "config": {"name": "num_layers", "default": null, "conditions": [], "min_value": 1, "max_value": 3, "step": 1, "sampling": "linear"}}, {"class_name": "Int", "config": {"name": "units_0", "default": null, "conditions": [], "min_value": 32, "max_value": 512, "step": 32, "sampling": "linear"}}, {"class_name": "Float", "config": {"name": "learning_rate", "default": 0.001, "conditions": [], "min_value": 0.0001, "max_value": 0.01, "step": null, "sampling": "log"}}, {"class_name": "Int", "config": {"name": "units_1", "default": null, "conditions": [], "min_value": 32, "max_value": 512, "step": 32, "sampling": "linear"}}, {"class_name": "Int", "config": {"name": "units_2", "default": null, "conditions": [], "min_value": 32, "max_value": 512, "step": 32, "sampling": "linear"}}], "values": {"num_layers": 1, "units_0": 32, "learning_rate": 0.001, "units_1": 32, "units_2": 32}}, "start_order": ["00", "01", "02"], "end_order": ["00", "01"], "run_times": {"00": 1, "01": 1}, "retry_queue": [], "seed": 4426, "seed_state": 4437, "tried_so_far": ["cf4e5c150be060ff93f41795e0a8cd78", "1be8c3daceabb6fa5007e252fca60392", "495cbd9e0628c7ff785c4763a27d280c"], "id_to_hash": {"00": "cf4e5c150be060ff93f41795e0a8cd78", "01": "1be8c3daceabb6fa5007e252fca60392", "02": "495cbd9e0628c7ff785c4763a27d280c"}, "display": {"search_start": "2024-06-19T15:52:38.122286", "trial_start": {"00": "2024-06-19T15:52:38.122286", "01": "2024-06-19T15:52:45.617347"}, "trial_number": {"00": 1, "01": 2}}}